matplotlib_fontja/__init__.py
matplotlib_fontja/matplotlib_fontja.py
matplotlib_fontja/fonts/IPA_Font_License_Agreement_v1.0.txt
matplotlib_fontja/fonts/Readme_ipaexg00401.txt
matplotlib_fontja/fonts/ipaexg.ttf
matplotlib_fontja-1.0.0.dist-info/METADATA
matplotlib_fontja-1.0.0.dist-info/WHEEL
matplotlib_fontja-1.0.0.dist-info/licenses/LICENSE
matplotlib_fontja-1.0.0.dist-info/RECORD
