Metadata-Version: 2.1
Name: matplotlib-fontja
Version: 1.0.0
Summary: matplotlibを日本語表示に対応させます。
Project-URL: Homepage, https://github.com/ciffelia/matplotlib-fontja
Project-URL: Repository, https://github.com/ciffelia/matplotlib-fontja.git
Project-URL: Issues, https://github.com/ciffelia/matplotlib-fontja/issues
Project-URL: Changelog, https://github.com/ciffelia/matplotlib-fontja/blob/master/CHANGELOG.md
Author-email: uehara1414 <akiya.noface@gmail.com>, Ciffelia <mc.prince.0203@gmail.com>
Maintainer-email: Ciffelia <mc.prince.0203@gmail.com>
License-File: LICENSE
Classifier: License :: OSI Approved :: MIT License
Requires-Dist: matplotlib
